[{"text": "chương trình 60 Giây chiều của đài", "start": 4.16, "duration": 3.099}, {"text": "truyền hình thành phố Hồ Chí Minh Xin", "start": 6.18, "duration": 2.879}, {"text": "kính chào quý vị thưa quý vị và công", "start": 7.259, "duration": 3.361}, {"text": "nghệ quý vị phải chờ đợi lâu ngay sau", "start": 9.059, "duration": 3.361}, {"text": "đây là các thông tin đáng chú ý Chiều", "start": 10.62, "duration": 4.099}, {"text": "Tối nay", "start": 12.42, "duration": 2.299}, {"text": "người tiêu dùng kỳ vọng giá tăng giảm sẽ", "start": 16.4, "duration": 5.16}, {"text": "tác động tích cực đến giá hàng hóa", "start": 19.26, "duration": 4.98}, {"text": "Sáng nay xuất hiện đang cá heo sát bờ", "start": 21.56, "duration": 4.78}, {"text": "biển Phú Yên", "start": 24.24, "duration": 4.64}, {"text": "[âm nhạc]", "start": 26.34, "duration": 4.98}, {"text": "giá xăng dầu vừa giảm mạnh sau nhiều lần", "start": 28.88, "duration": 4.0}, {"text": "điều chỉnh với những tín hiệu tích cực", "start": 31.32, "duration": 3.12}, {"text": "này người dân thành phố Hồ Chí Minh kỳ", "start": 32.88, "duration": 3.78}, {"text": "vọng giá hàng hóa thiết yếu sẽ sớm ổn", "start": 34.44, "duration": 3.959}, {"text": "định trong thời gian tới sau thời gian", "start": 36.66, "duration": 4.02}, {"text": "đổi giá nhằm giảm áp lực chi tiêu sinh", "start": 38.399, "duration": 4.5}, {"text": "hoạt ghi nhận của phóng viên chương", "start": 40.68, "duration": 4.26}, {"text": "trình tại các chợ và siêu thị trong ngày", "start": 42.899, "duration": 5.241}, {"text": "mua sắm cuối tuần sáng nay", "start": 44.94, "duration": 6.42}, {"text": "đi chợ truyền thống ngày cuối tuần giá", "start": 48.14, "duration": 4.84}, {"text": "nhiều mặt hàng chưa thể giảm theo giá", "start": 51.36, "duration": 4.32}, {"text": "xăng thậm chí có mặt hàng thực phẩm còn", "start": 52.98, "duration": 6.96}, {"text": "có xu hướng tăng nhẹ tăng ơi", "start": 55.68, "duration": 6.359}, {"text": "Bây giờ em nó đang nhích Lên Cứ mỗi ngày", "start": 59.94, "duration": 4.679}, {"text": "ngàn 2 ngàn coi như một tuần lễ nay là", "start": 62.039, "duration": 4.701}, {"text": "hơn 10.000 rồi", "start": 64.619, "duration": 5.0}, {"text": "sức mua mình nó giảm đi còn", "start": 66.74, "duration": 5.34}, {"text": "mất 30%", "start": 69.619, "duration": 5.021}, {"text": "còn tại hệ thống siêu thị giá các mặt", "start": 72.08, "duration": 4.3}, {"text": "hàng tiêu dùng thiết yếu hầu như không", "start": 74.64, "duration": 4.019}, {"text": "có sự biến động vì nhiều sản phẩm nằm", "start": 76.38, "duration": 3.919}, {"text": "trong chương trình bệnh Ổn của thành phố", "start": 78.659, "duration": 4.14}, {"text": "Ngoài ra thì chúng tôi cũng cùng với Sở", "start": 80.299, "duration": 4.0}, {"text": "Công thương phát triển ra một cái chương", "start": 82.799, "duration": 3.661}, {"text": "trình gọi là giá sỉ tức là chúng tôi", "start": 84.299, "duration": 4.441}, {"text": "muốn người tiêu dùng có thể tận hưởng", "start": 86.46, "duration": 6.08}, {"text": "được mua giá sỉ tại cái hệ thống bán lẻ", "start": 88.74, "duration": 6.78}, {"text": "khi giá xăng dầu giảm cần tính toán lại", "start": 92.54, "duration": 4.66}, {"text": "để có mức giá các mặt hàng tiêu dùng", "start": 95.52, "duration": 4.68}, {"text": "tương xứng Tuy nhiên trên thực tế để giá", "start": 97.2, "duration": 5.099}, {"text": "các hàng hóa tiêu dùng giảm bao giờ cũng", "start": 100.2, "duration": 4.02}, {"text": "cần một độ Trễ nhất định so với thời", "start": 102.299, "duration": 4.161}, {"text": "điểm giảm giá xăng", "start": 104.22, "duration": 4.56}, {"text": "Trung tâm quản lý giao thông công cộng", "start": 106.46, "duration": 4.24}, {"text": "thành phố Hồ Chí Minh vừa đề xuất áp", "start": 108.78, "duration": 4.14}, {"text": "dụng giá vé Metro cao nhất 24.000 đồng", "start": 110.7, "duration": 3.959}, {"text": "một lượt mức này được thử nghiệm cho", "start": 112.92, "duration": 4.08}, {"text": "giai đoạn đầu cho tuyến Metro số 1 sau", "start": 114.659, "duration": 3.96}, {"text": "một năm sẽ đánh giá lại để phù hợp với", "start": 117.0, "duration": 3.619}, {"text": "thực tế", "start": 118.619, "duration": 4.201}, {"text": "Trung tâm quản lý giao thông công cộng", "start": 120.619, "duration": 4.241}, {"text": "thành phố Hồ Chí Minh đã căn cứ vào báo", "start": 122.82, "duration": 3.96}, {"text": "cáo của chủ đầu tư là ban quản lý đường", "start": 124.86, "duration": 4.259}, {"text": "sắt đô thị về phương án giá vé để đề", "start": 126.78, "duration": 4.679}, {"text": "xuất các mức giá giá vé được đề xuất", "start": 129.119, "duration": 4.681}, {"text": "theo từng loại cụ thể như sau giá giấy", "start": 131.459, "duration": 5.401}, {"text": "lược từ 9.000 đến 24000₫ một lượt giá", "start": 133.8, "duration": 4.799}, {"text": "giấy lược thanh toán bằng thẻ nạp từ", "start": 136.86, "duration": 4.44}, {"text": "7.000 đến 18.000 đồng một lượt giá giá", "start": 138.599, "duration": 5.461}, {"text": "ngày là 48.000 đồng một ngày giá dán sử", "start": 141.3, "duration": 5.88}, {"text": "dụng 3 ngày là 108.000 đồng Bên cạnh đó", "start": 144.06, "duration": 5.22}, {"text": "giá vé tháng áp dụng cho hành khách phổ", "start": 147.18, "duration": 5.1}, {"text": "thông là 330.000 đồng một tháng giá giá", "start": 149.28, "duration": 4.819}, {"text": "áp dụng cho học sinh sinh viên là", "start": 152.28, "duration": 4.819}, {"text": "165.000 đồng một tháng", "start": 154.099, "duration": 5.681}, {"text": "vào sáng hôm qua cầu thép An Phú Đông", "start": 157.099, "duration": 4.841}, {"text": "bắc qua sông Vàm Thuận núi quận 12 và", "start": 159.78, "duration": 4.2}, {"text": "quận Gò Vấp thành phố Hồ Chí Minh bị sà", "start": 161.94, "duration": 4.019}, {"text": "lan tông biến dạng vượt trội ngay sau sự", "start": 163.98, "duration": 3.36}, {"text": "cố cơ quan chức năng Thành phố Hồ Chí", "start": 165.959, "duration": 3.661}, {"text": "Minh đang khẩn trương kiểm tra đánh giá", "start": 167.34, "duration": 3.96}, {"text": "hiện trạng để xác định các biện pháp", "start": 169.62, "duration": 5.54}, {"text": "khắc phục sửa chữa ghi nhận và sáng nay", "start": 171.3, "duration": 7.86}, {"text": "khoảng 7h-0", "start": 175.16, "duration": 4.0}, {"text": "774 kéo theo xà lan chạy trên sông Vàm", "start": 179.819, "duration": 4.741}, {"text": "thuật hướng từ sông Sài Gòn về cầu An", "start": 182.64, "duration": 4.92}, {"text": "Lộc quận 12 khi đến cầu An Phú Đông Tàu", "start": 184.56, "duration": 5.7}, {"text": "tông vào trụ t6 của công trình làm cong", "start": 187.56, "duration": 5.52}, {"text": "vênh xê dịch khỏi vị trí ban đầu trước", "start": 190.26, "duration": 5.1}, {"text": "mắt để đảm bảo an toàn giao thông sở", "start": 193.08, "duration": 4.32}, {"text": "giao thông vận tải cấm tất cả ô tô lưu", "start": 195.36, "duration": 4.2}, {"text": "thông qua cầu xe 2 bánh vẫn lưu thông", "start": 197.4, "duration": 4.199}, {"text": "Bình thường để tiến hành kiểm tra sửa", "start": 199.56, "duration": 4.8}, {"text": "chữa cầu sau khi kiểm tra nó chỉ ảnh", "start": 201.599, "duration": 5.401}, {"text": "hưởng đến duy nhất cái cái trụ số 6 các", "start": 204.36, "duration": 5.76}, {"text": "hệ thống dầm và mặt cầu của cầu thì đều", "start": 207.0, "duration": 5.28}, {"text": "ổn định chúng tôi cũng đang tiến hành là", "start": 210.12, "duration": 4.92}, {"text": "khắc phục Sơ Bộ lại cái cái hư hỏng và", "start": 212.28, "duration": 4.92}, {"text": "lập phương án để báo cáo sở giao thông", "start": 215.04, "duration": 4.68}, {"text": "và các cơ quan chức năng để có các biện", "start": 217.2, "duration": 4.86}, {"text": "pháp xử lý triệt để trong thời gian sớm", "start": 219.72, "duration": 4.26}, {"text": "nhất cầu An Phú Đông giúp rút ngắn thời", "start": 222.06, "duration": 3.72}, {"text": "gian đi từ quận 12 Vào trung tâm thành", "start": 223.98, "duration": 4.86}, {"text": "phố không chỉ cầu An Phú Đông thời gian", "start": 225.78, "duration": 4.98}, {"text": "qua nhiều cầu ở thành phố Hồ Chí Minh bị", "start": 228.84, "duration": 5.6}, {"text": "tàu xà lan tông làm ảnh hưởng Công trình", "start": 230.76, "duration": 6.539}, {"text": "hồ Trị An ở Đồng Nai nơi cung cấp nước", "start": 234.44, "duration": 4.84}, {"text": "cho thủy điện Trị An và nước sinh hoạt", "start": 237.299, "duration": 3.781}, {"text": "cho hàng triệu người dân vùng Hà Lưu", "start": 239.28, "duration": 3.06}, {"text": "Đồng Nai Bình Dương thành phố Hồ Chí", "start": 241.08, "duration": 3.48}, {"text": "Minh đang trong tình trạng cản trời đấy", "start": 242.34, "duration": 4.5}, {"text": "nhiều nơi ở lòng hồ đang phơi mình dưới", "start": 244.56, "duration": 5.42}, {"text": "cái nắng trong mùa khô hạn", "start": 246.84, "duration": 6.119}, {"text": "theo ghi nhận hiện nay hồ Trị An đã cản", "start": 249.98, "duration": 5.08}, {"text": "trở đấy nước rút xa nhiều cây số tính từ", "start": 252.959, "duration": 4.441}, {"text": "bờ Hồ Suốt dọc đường đi từ bờ hồ Trị An", "start": 255.06, "duration": 4.739}, {"text": "vào sâu trong lòng hồ đất khô cằn nứt nẻ", "start": 257.4, "duration": 4.579}, {"text": "nước chỉ còn ở lòng sông và Các suối nhỏ", "start": 259.799, "duration": 4.561}, {"text": "công ty thủy điện Trị An huyện Vĩnh Cửu", "start": 261.979, "duration": 5.081}, {"text": "cho biết sáng 14/5 mực nước hồ đo được", "start": 264.36, "duration": 5.94}, {"text": "là 51m chỉ cách mực nước chết 1m Trong", "start": 267.06, "duration": 4.859}, {"text": "khi mực nước dân bình thường của hộ là", "start": 270.3, "duration": 4.26}, {"text": "62m đây là mực nước thấp nhất đo được", "start": 271.919, "duration": 5.161}, {"text": "tại hồ Trị An trong hơn 10 năm qua theo", "start": 274.56, "duration": 4.38}, {"text": "người dân địa phương hồ Trị An thường có", "start": 277.08, "duration": 3.36}, {"text": "đỉnh điểm khô hạn vào khoảng thời gian", "start": 278.94, "duration": 4.68}, {"text": "tháng 5 6 hàng năm công ty thủy điện Trị", "start": 280.44, "duration": 5.039}, {"text": "An cho biết đã nhận được văn bản hỏa tốc", "start": 283.62, "duration": 3.9}, {"text": "từ tập đoàn điện lực Việt Nam về việc", "start": 285.479, "duration": 3.72}, {"text": "thực hiện các giải pháp cấp bách giảm", "start": 287.52, "duration": 3.3}, {"text": "thiểu nguy cơ thiếu nước cấp cho Hạ Du", "start": 289.199, "duration": 3.78}, {"text": "trong thời gian còn lại của mùa khô 2023", "start": 290.82, "duration": 4.92}, {"text": "công ty thủy điện Trị An sẽ chủ động làm", "start": 292.979, "duration": 4.5}, {"text": "việc với địa phương lập kế hoạch sử dụng", "start": 295.74, "duration": 3.66}, {"text": "nước tiết kiệm khai thác nguồn nước phục", "start": 297.479, "duration": 4.321}, {"text": "vụ sinh hoạt và sản xuất phù hợp với kế", "start": 299.4, "duration": 4.2}, {"text": "hoạch vận hành xả nước của nhà máy tránh", "start": 301.8, "duration": 3.92}, {"text": "lãng phí nguồn nước", "start": 303.6, "duration": 5.099}, {"text": "khoảng 9h30 Sáng nay nhiều du khách ở", "start": 305.72, "duration": 4.78}, {"text": "Phú Yên đã được chứng kiến một hiện", "start": 308.699, "duration": 3.841}, {"text": "tượng kỳ thú hàng chục con cá heo xuất", "start": 310.5, "duration": 3.9}, {"text": "hiện và nhảy múa gần thắng cảnh mũi điện", "start": 312.54, "duration": 4.14}, {"text": "thì xã Đông Hòa hiện tượng hiếm thấy này", "start": 314.4, "duration": 4.2}, {"text": "nhanh chóng thu hút nhiều chú ý của cư", "start": 316.68, "duration": 4.16}, {"text": "dân mạng", "start": 318.6, "duration": 2.24}, {"text": "người quay đoạn clip trên là hướng dẫn", "start": 321.199, "duration": 4.661}, {"text": "viên du lịch gian Duy Anh cho biết khi", "start": 323.759, "duration": 3.841}, {"text": "đang dẫn khách tham quan mũi điện thì", "start": 325.86, "duration": 3.96}, {"text": "bắt gặp đàn cá heo hơn chục con bơi rất", "start": 327.6, "duration": 4.26}, {"text": "nhanh quanh khu vực này Đây là lần đầu", "start": 329.82, "duration": 3.84}, {"text": "tiên anh thấy đàn cá heo đông như vậy", "start": 331.86, "duration": 4.2}, {"text": "clip quay đàn cá heo sau đó được người", "start": 333.66, "duration": 4.68}, {"text": "trong đoàn đăng tải lên mạng xã hội đã", "start": 336.06, "duration": 4.139}, {"text": "ngay lập tức Nhận được sự chú ý của cư", "start": 338.34, "duration": 4.199}, {"text": "dân mạng nhiều người tỏ ra thích thú khi", "start": 340.199, "duration": 4.44}, {"text": "chứng kiến đàn cá heo bơi lội số khác", "start": 342.539, "duration": 4.021}, {"text": "nhận định giữa cá heo bơi sát vào bờ", "start": 344.639, "duration": 4.141}, {"text": "chứng tỏ nguồn nước ở đây sạch và thức", "start": 346.56, "duration": 4.56}, {"text": "ăn dồi dào cá heo là động vật có vú", "start": 348.78, "duration": 4.68}, {"text": "thường cư ngụ ở các vùng biển Đông thành", "start": 351.12, "duration": 5.84}, {"text": "đàn từ hàng chục tới hàng trăm con", "start": 353.46, "duration": 5.88}, {"text": "sau nhiều cảnh báo nhiễm bệnh nặng sau", "start": 356.96, "duration": 4.42}, {"text": "khi ăn tình trạng ăn các món tiết canh", "start": 359.34, "duration": 4.02}, {"text": "động vật đã giảm nhiều Tuy nhiên ở nhiều", "start": 361.38, "duration": 4.379}, {"text": "nơi đặc biệt là nông thôn vùng sâu vùng", "start": 363.36, "duration": 4.5}, {"text": "xa nhiều người vẫn ăn tiết canh và phải", "start": 365.759, "duration": 3.481}, {"text": "nhập viện trong tình trạng nguy hiểm", "start": 367.86, "duration": 5.0}, {"text": "tính mạng ghi nhận ở Đắk Lắk", "start": 369.24, "duration": 6.299}, {"text": "cách đây hơn 10 ngày một bệnh nhân Nam", "start": 372.86, "duration": 5.38}, {"text": "44 tuổi ở huyện Krông Pắk đã ăn tiết", "start": 375.539, "duration": 4.681}, {"text": "canh và tham gia mổ heo tại một đám giỗ", "start": 378.24, "duration": 4.62}, {"text": "sau khi ăn khoảng 5 tiếng đồng hồ bệnh", "start": 380.22, "duration": 4.62}, {"text": "nhân có biểu hiện sốt cao liên tục đau", "start": 382.86, "duration": 5.1}, {"text": "đầu đau bụng ù tai sau 3 ngày điều trị", "start": 384.84, "duration": 4.919}, {"text": "tại nhà bệnh nhân được chuyển lên bệnh", "start": 387.96, "duration": 3.66}, {"text": "viện đa khoa vùng Tây Nguyên trong tình", "start": 389.759, "duration": 4.44}, {"text": "trạng nguy kịch tại đây Các bác sĩ đã", "start": 391.62, "duration": 4.74}, {"text": "làm xét nghiệm kết quả cho thấy bệnh", "start": 394.199, "duration": 4.321}, {"text": "nhân bị viêm màng não mủ do liên cầu lợn", "start": 396.36, "duration": 5.22}, {"text": "hiện tại Bệnh nhân vẫn còn đau đầu nhẹ", "start": 398.52, "duration": 6.66}, {"text": "và có một cái rối loạn tiền đình dẫn đến", "start": 401.58, "duration": 6.239}, {"text": "điện đây là một cái triệu chứng cũng là", "start": 405.18, "duration": 5.1}, {"text": "điển hình của liên cầu lớn theo các bác", "start": 407.819, "duration": 5.341}, {"text": "sĩ 70% bệnh nhân mắc liên cầu lợn là do", "start": 410.28, "duration": 5.34}, {"text": "ăn tiết canh bệnh này hiện chưa có vắc", "start": 413.16, "duration": 5.46}, {"text": "xin điều trị vì vậy để phòng bệnh các", "start": 415.62, "duration": 4.74}, {"text": "bác sĩ khuyến cáo người lên không nên ăn", "start": 418.62, "duration": 3.66}, {"text": "tiết canh và các nội tạng động vật chưa", "start": 420.36, "duration": 4.26}, {"text": "được nấu chín những người chăn nuôi chế", "start": 422.28, "duration": 4.139}, {"text": "biến gia súc nên đeo găng tay và các", "start": 424.62, "duration": 3.299}, {"text": "phương tiện phòng hộ khi tiếp xúc với", "start": 426.419, "duration": 4.141}, {"text": "thịt heo tái sống và khi có các triệu", "start": 427.919, "duration": 4.741}, {"text": "chứng của bệnh cần đến ngay các cơ sở y", "start": 430.56, "duration": 5.6}, {"text": "tế để thăm khám điều trị kịp thời", "start": 432.66, "duration": 7.02}, {"text": "ở phần thế giới cập nhật nhờ điện cực", "start": 436.16, "duration": 5.68}, {"text": "mềm phẫu thuật não có thể sẽ ít xâm lấn", "start": 439.68, "duration": 4.28}, {"text": "hơn", "start": 441.84, "duration": 2.12}, {"text": "và phát hiện điều bí ẩn trong tranh của", "start": 445.58, "duration": 5.94}, {"text": "Picasso", "start": 448.68, "duration": 2.84}, {"text": "[âm nhạc]", "start": 454.44, "duration": 4.319}, {"text": "các nhà khoa học tại trường đại học Bách", "start": 456.139, "duration": 4.721}, {"text": "Khoa Liên bang Thụy Sĩ đã phát triển một", "start": 458.759, "duration": 4.261}, {"text": "điện cực để theo dõi bộ não thiết bị này", "start": 460.86, "duration": 4.619}, {"text": "được đưa vào bên trong vỏ não thông qua", "start": 463.02, "duration": 5.399}, {"text": "một lỗ nhỏ trên hộp sọ và sẽ bung ra mà", "start": 465.479, "duration": 6.201}, {"text": "không cần phải xâm lấn quá nhiều", "start": 468.419, "duration": 6.301}, {"text": "mảng điện cực có 6 cánh hình xoắn Mỗi", "start": 471.68, "duration": 4.84}, {"text": "cánh được triển khai một lần trên mô mềm", "start": 474.72, "duration": 3.96}, {"text": "của não nhờ cơ chế kích hoạt Lấy cảm", "start": 476.52, "duration": 4.679}, {"text": "hứng từ công nghệ robot mềm cơ chế bung", "start": 478.68, "duration": 4.26}, {"text": "ra giống giới sẽ phát triển của rễ cây", "start": 481.199, "duration": 3.9}, {"text": "và cho phép triển khai bất kỳ kết thúc", "start": 482.94, "duration": 4.22}, {"text": "nào của điện cực với áp lực nhẹ lên não", "start": 485.099, "duration": 4.261}, {"text": "mảng điều cực này đã được thử nghiệm", "start": 487.16, "duration": 4.24}, {"text": "thành công trên một chú heo con và đang", "start": 489.36, "duration": 4.2}, {"text": "được công ty newlosoft Bio Electronic", "start": 491.4, "duration": 4.62}, {"text": "phát triển thêm chúng tôi nghĩ rằng công", "start": 493.56, "duration": 4.259}, {"text": "nghệ này có thể triển khai rộng rãi do", "start": 496.02, "duration": 4.44}, {"text": "tính ít xâm lấn Vì vậy chúng tôi hi vọng", "start": 497.819, "duration": 4.741}, {"text": "mở rộng công nghệ này để phù hợp với con", "start": 500.46, "duration": 4.2}, {"text": "người và tăng số lượng điện cực để có", "start": 502.56, "duration": 3.859}, {"text": "được thông tin chi tiết hơn giờ não", "start": 504.66, "duration": 4.02}, {"text": "nghiên cứu được xuất bản trên tạp chí", "start": 506.419, "duration": 5.5}, {"text": "science có thể cung cấp các giải pháp ít", "start": 508.68, "duration": 6.68}, {"text": "xâm lấn cho bệnh nhân mắc bệnh động kinh", "start": 511.919, "duration": 6.24}, {"text": "nổi tiếng với mình thú nhưng mỏ chân có", "start": 515.36, "duration": 5.32}, {"text": "mặt và cựa có nọc độc thú mỏ vịt là một", "start": 518.159, "duration": 4.021}, {"text": "trong hai loài động vật có vú đẻ trứng", "start": 520.68, "duration": 3.659}, {"text": "duy nhất trên thế giới ngày 12 tháng 5", "start": 522.18, "duration": 4.62}, {"text": "chính quyền bang New South Wales đã thả", "start": 524.339, "duration": 4.56}, {"text": "4 con thú mỏ vịt cái ở công viên quốc", "start": 526.8, "duration": 4.5}, {"text": "gia hoàng gia phía Nam Sydney việc đưa", "start": 528.899, "duration": 4.38}, {"text": "loài thú này trở lại công viên nằm trong", "start": 531.3, "duration": 3.96}, {"text": "chương trình phục hồi thú mỏ vịt ở bang", "start": 533.279, "duration": 4.581}, {"text": "New South Wales", "start": 535.26, "duration": 2.6}, {"text": "đến ngày 20 của đại học New South số lần", "start": 539.399, "duration": 4.261}, {"text": "nhìn thấy thú mỏ vịt được ghi lại trong", "start": 541.92, "duration": 4.88}, {"text": "30 năm qua ở bang này đã giảm gần 1/3", "start": 543.66, "duration": 5.58}, {"text": "môi trường sống bị hủy hoại suy thoái", "start": 546.8, "duration": 4.36}, {"text": "sông ngòi thời tiết khắc nghiệt do biến", "start": 549.24, "duration": 4.38}, {"text": "đổi khí hậu là những lý do chính khiến", "start": 551.16, "duration": 5.28}, {"text": "số lượng thú mỏ vịt đang giảm dần hi", "start": 553.62, "duration": 4.44}, {"text": "vọng rằng chúng sẽ có thể thiết lập một", "start": 556.44, "duration": 3.959}, {"text": "quần thể mới và phát triển mạnh ở công", "start": 558.06, "duration": 5.1}, {"text": "viên quốc gia hoàng gia không giống như", "start": 560.399, "duration": 5.461}, {"text": "gấu kola hay Kangaroo hầu hết người ở", "start": 563.16, "duration": 4.619}, {"text": "Australia chưa bao giờ nhìn thấy thú mỏ", "start": 565.86, "duration": 4.08}, {"text": "vịt trong tự nhiên do tính chất ẩn dật", "start": 567.779, "duration": 4.261}, {"text": "và nhu cầu môi trường sống đặc biệt cao", "start": 569.94, "duration": 4.98}, {"text": "của chúng mỗi con thú mỏ vịt ở lợn thả", "start": 572.04, "duration": 4.919}, {"text": "này sẽ được theo dõi sát sao trong 2 năm", "start": 574.92, "duration": 4.979}, {"text": "tới ngoài ra chính phủ sẽ can thiệp để", "start": 576.959, "duration": 4.621}, {"text": "di chuyển chúng sang nơi khác trong", "start": 579.899, "duration": 3.861}, {"text": "trường hợp hạn hán cháy rừng hoặc lũ lụt", "start": 581.58, "duration": 4.98}, {"text": "ở đợt tiếp theo cơ quan môi trường sẽ", "start": 583.76, "duration": 5.32}, {"text": "thả thêm 6 con khác bao gồm hai con cái", "start": 586.56, "duration": 5.36}, {"text": "và bốn con đực", "start": 589.08, "duration": 2.84}, {"text": "Hôm nay ngày chủ nhật thứ hai trong", "start": 592.58, "duration": 4.3}, {"text": "tháng 5 là ngày được nhiều nước phương", "start": 595.2, "duration": 4.199}, {"text": "tây xem là ngày của mẹ theo thời gian", "start": 596.88, "duration": 4.44}, {"text": "này đã nhân rộng ra nhiều nước với ý", "start": 599.399, "duration": 3.781}, {"text": "nghĩa tôn vinh sự hi sinh lớn lao và", "start": 601.32, "duration": 3.78}, {"text": "biết ơn người mẹ các hoạt động tri ân", "start": 603.18, "duration": 5.42}, {"text": "nghề của mẹ khá đa dạng tại nhiều nước", "start": 605.1, "duration": 3.5}, {"text": "nhiều người tặng quà để cảm ơn mẹ về", "start": 609.26, "duration": 5.259}, {"text": "tình yêu và sự động viên Ngoài ra người", "start": 612.06, "duration": 4.56}, {"text": "anh còn có phong tục làm bánh ximen để", "start": 614.519, "duration": 5.041}, {"text": "tặng mẹ còn tại Australia các em nhỏ", "start": 616.62, "duration": 5.04}, {"text": "giết thiệt và tặng quà để bày tỏ lòng", "start": 619.56, "duration": 4.38}, {"text": "biết ơn đấng sinh thành người Australia", "start": 621.66, "duration": 3.84}, {"text": "cũng có truyền thống đeo hoa cẩm chướng", "start": 623.94, "duration": 4.26}, {"text": "trong ngày này trong đó qua màu trắng để", "start": 625.5, "duration": 4.8}, {"text": "tưởng nhớ người mẹ đã khuất còn qua màu", "start": 628.2, "duration": 4.68}, {"text": "để thể hiện lòng biết ơn khi mẹ vẫn còn", "start": 630.3, "duration": 5.34}, {"text": "sống tại Mỹ ngày của mẹ là một trong", "start": 632.88, "duration": 4.68}, {"text": "những ngày lễ lớn hàng năm những người", "start": 635.64, "duration": 3.66}, {"text": "con trong gia đình có truyền thống mời", "start": 637.56, "duration": 3.839}, {"text": "mẹ ăn tối hoặc nấu cho mẹ một bữa ăn", "start": 639.3, "duration": 4.74}, {"text": "trong dịp này trẻ em tại Mỹ thường chuẩn", "start": 641.399, "duration": 4.62}, {"text": "bị một tiết mục văn nghệ Như hát hoặc", "start": 644.04, "duration": 4.62}, {"text": "diễn kịch để tặng mẹ hoặc bà những người", "start": 646.019, "duration": 6.981}, {"text": "trưởng thành lại mua tặng mẹ hoa và quà", "start": 648.66, "duration": 6.72}, {"text": "khách vào tham quan sở thú thích thú", "start": 653.0, "duration": 4.06}, {"text": "ngắm các động vật mới chào đời tại đây", "start": 655.38, "duration": 3.959}, {"text": "sự kiện đặc biệt này được tổ chức nhân", "start": 657.06, "duration": 6.68}, {"text": "của mẹ tại Sở thú ở thủ đô Lima của Peru", "start": 659.339, "duration": 7.021}, {"text": "để mừng ngày của mẹ diễn ra vào ngày 14", "start": 663.74, "duration": 5.38}, {"text": "tháng 5 một sở thú ở Peru Đã mời du", "start": 666.36, "duration": 4.44}, {"text": "khách đến gặp những thành viên rất đáng", "start": 669.12, "duration": 4.74}, {"text": "yêu nhỏ tuổi nhất của mình sự ra đời của", "start": 670.8, "duration": 4.5}, {"text": "những con vật này khiến chúng tôi hạnh", "start": 673.86, "duration": 3.659}, {"text": "phúc vì việc này góp phần vào sự bảo tồn", "start": 675.3, "duration": 5.279}, {"text": "các loài này vào ngày của mẹ chúng tôi", "start": 677.519, "duration": 4.861}, {"text": "muốn nhắc nhở rằng công ơn của những", "start": 680.579, "duration": 5.221}, {"text": "người mẹ rất quý giá tại đây du khách có", "start": 682.38, "duration": 5.579}, {"text": "thể ngắm những con thú con như Kangaroo", "start": 685.8, "duration": 5.7}, {"text": "Lạc đà viruna khỉ video mai vô Titi trâu", "start": 687.959, "duration": 5.961}, {"text": "nước và khu đuôi trắng bên mẹ của chúng", "start": 691.5, "duration": 5.339}, {"text": "một số khách tham quan cho biết họ chưa", "start": 693.92, "duration": 6.0}, {"text": "từng thấy những hình ảnh như thế này", "start": 696.839, "duration": 3.081}, {"text": "công nghệ hình ảnh hiện đại vừa giúp các", "start": 699.98, "duration": 4.06}, {"text": "chuyên gia vẽ tranh phát hiện hình ảnh", "start": 702.48, "duration": 4.08}, {"text": "một chú chó nhỏ ẩn sau một bức tranh", "start": 704.04, "duration": 4.919}, {"text": "thời kỳ đầu của danh họa bập lô Picasso", "start": 706.56, "duration": 4.32}, {"text": "những người đam mê hội họa Đang háo hức", "start": 708.959, "duration": 4.201}, {"text": "bàn tán trên mạng xã hội và Tìm câu trả", "start": 710.88, "duration": 7.459}, {"text": "lời tại sao chú chó nhỏ lại lại bị ẩn đi", "start": 713.16, "duration": 5.179}, {"text": "sử dụng máy quang phổ hình ảnh huỳnh", "start": 719.279, "duration": 3.781}, {"text": "quang tia X các nhà nghiên cứu tại bảo", "start": 720.839, "duration": 4.861}, {"text": "tàng Garena ở thành phố New York Mỹ đã", "start": 723.06, "duration": 4.5}, {"text": "phát hiện ra sự hiện diện của một chú", "start": 725.7, "duration": 4.74}, {"text": "chó nhỏ nó nằm ở lớp dưới cùng của bức", "start": 727.56, "duration": 5.82}, {"text": "tranh lơ Mu Lan deles được quy cách xô", "start": 730.44, "duration": 5.72}, {"text": "vẽ ở độ tuổi 19 khi ông sống ở Paris", "start": 733.38, "duration": 5.459}, {"text": "nhìn vào chỗ này có thể thấy các mảng", "start": 736.16, "duration": 5.08}, {"text": "màu sụt qua và có kết cấu không liên", "start": 738.839, "duration": 4.861}, {"text": "quan đến bố cục cuối cùng lúc đó tôi có", "start": 741.24, "duration": 4.5}, {"text": "một cảm giác rất mạnh rằng dường như có", "start": 743.7, "duration": 4.1}, {"text": "cái gì đó nằm ở bên dưới", "start": 745.74, "duration": 4.38}, {"text": "trước đó các chuyên gia đã nghiên cứu", "start": 747.8, "duration": 4.18}, {"text": "tác phẩm này trong nhiều năm nhưng không", "start": 750.12, "duration": 4.2}, {"text": "phát hiện hình vẽ nào bên dưới chú chó", "start": 751.98, "duration": 4.38}, {"text": "Trong hình vẽ có thể là giống spaniel", "start": 754.32, "duration": 5.12}, {"text": "rất phổ biến ở Paris vào thời điểm đó", "start": 756.36, "duration": 5.58}, {"text": "chú chó Đã hoàn toàn thay đổi cách mà", "start": 759.44, "duration": 4.54}, {"text": "người ta nhìn ngắm bức tranh này Nó thực", "start": 761.94, "duration": 4.199}, {"text": "sự đáng yêu đang nhìn thẳng vào chúng ta", "start": 763.98, "duration": 5.52}, {"text": "với chiếc nơ đỏ tuyệt vời này bức tranh", "start": 766.139, "duration": 4.921}, {"text": "nói trên là một trong những kiệt tác đầu", "start": 769.5, "duration": 3.779}, {"text": "tiên của Picasso đã nằm trong bộ sưu tập", "start": 771.06, "duration": 4.26}, {"text": "của bảo tàng Garena ở New York trong", "start": 773.279, "duration": 4.86}, {"text": "nhiều thập kỷ thưa quý vị Chiều nay một", "start": 775.32, "duration": 4.86}, {"text": "căn nhà 4 tầng trên Hưng Hóa Quận Tân", "start": 778.139, "duration": 3.181}, {"text": "Bình Thành phố Hồ Chí Minh bốc cháy", "start": 780.18, "duration": 2.88}, {"text": "khiến nhiều người dân hoảng loạn tháo", "start": 781.32, "duration": 3.98}, {"text": "chạy thoát thân", "start": 783.06, "duration": 4.92}, {"text": "theo người dân ở hiện trường lửa phát ra", "start": 785.3, "duration": 5.02}, {"text": "từ lầu 3 của căn nhà lúc này nhiều người", "start": 787.98, "duration": 4.08}, {"text": "sống trong căn nhà liền tháo chạy ra", "start": 790.32, "duration": 4.019}, {"text": "ngoài hô hoán Họ quay lại lầu 3 dùng", "start": 792.06, "duration": 4.26}, {"text": "bình chữa cháy mini cố dập lửa nhưng", "start": 794.339, "duration": 4.141}, {"text": "không thành nhận tin báo đội cảnh sát", "start": 796.32, "duration": 3.9}, {"text": "phòng cháy chữa cháy và cứu nạn cứu hộ", "start": 798.48, "duration": 3.9}, {"text": "công an quận Tân Bình đã điều nhiều xe", "start": 800.22, "duration": 3.84}, {"text": "chữa cháy và hàng chục cán bộ chiến sĩ", "start": 802.38, "duration": 4.139}, {"text": "đến hiện trường khoảng 15 phút sau vụ", "start": 804.06, "duration": 4.38}, {"text": "cháy cơ bản được khống chế không có", "start": 806.519, "duration": 3.661}, {"text": "thương vong về người nhưng nhiều tài sản", "start": 808.44, "duration": 3.959}, {"text": "bị thiêu rụi nguyên nhân vụ cháy đang", "start": 810.18, "duration": 4.219}, {"text": "được điều tra", "start": 812.399, "duration": 4.62}, {"text": "công an thị xã Ba Đồn tỉnh Quảng Bình", "start": 814.399, "duration": 4.781}, {"text": "cho biết nơi đây đang điều tra vụ một", "start": 817.019, "duration": 4.141}, {"text": "người đàn ông cầm súng đến nhà chủ nợ", "start": 819.18, "duration": 4.26}, {"text": "bắn loạn xạ đối tượng này là Nguyễn Đức", "start": 821.16, "duration": 5.66}, {"text": "Quý đã bị công an bắt giữ", "start": 823.44, "duration": 5.76}, {"text": "Theo thông tin ban đầu chiều ngày 12", "start": 826.82, "duration": 4.72}, {"text": "tháng 5 đối tượng Nguyễn Đức Quý Do có", "start": 829.2, "duration": 4.259}, {"text": "mâu thuẫn với ông phan cô viết trú tại", "start": 831.54, "duration": 3.66}, {"text": "phường Quảng Thọ nên đã xông vào nhà", "start": 833.459, "duration": 4.32}, {"text": "dùng súng bắn liên tiếp 6 phát đạn may", "start": 835.2, "duration": 4.319}, {"text": "mắn là không gây thương vong cho người", "start": 837.779, "duration": 3.961}, {"text": "nào không những nổ súng ông Quý còn dùng", "start": 839.519, "duration": 4.62}, {"text": "súng chỉ vào người và đe dọa ông vích và", "start": 841.74, "duration": 4.62}, {"text": "mẹ ông vích dù việc đã gây náo loạn cả", "start": 844.139, "duration": 4.38}, {"text": "khu dân cư quanh nhà ông vích ngay trong", "start": 846.36, "duration": 4.2}, {"text": "đêm 12 tháng 5 cơ quan chức năng đã bắt", "start": 848.519, "duration": 4.141}, {"text": "khẩn cấp đối tượng quý theo người nhà", "start": 850.56, "duration": 3.839}, {"text": "ông vích quý trước đó có mua dược liệu", "start": 852.66, "duration": 3.6}, {"text": "xây dựng tại cửa hàng của ông vích để", "start": 854.399, "duration": 4.261}, {"text": "xây nhà Tuy nhiên quý không trả hết tiền", "start": 856.26, "duration": 5.22}, {"text": "mà nợ lại 25 triệu đồng đến chiều 12", "start": 858.66, "duration": 5.28}, {"text": "tháng 5 thì quý đem xuống đến gây ra vụ", "start": 861.48, "duration": 4.32}, {"text": "việc nói trên cơ quan công an cũng đang", "start": 863.94, "duration": 3.899}, {"text": "điều tra nguồn gốc súng dài đạn mà Quý", "start": 865.8, "duration": 5.24}, {"text": "đã sử dụng để bắn vào nhà ông vích", "start": 867.839, "duration": 5.641}, {"text": "công an tỉnh Nghệ An vừa kiểm tra nhiều", "start": 871.04, "duration": 4.0}, {"text": "điểm kinh doanh tại huyện Diễn Châu", "start": 873.48, "duration": 3.419}, {"text": "thành phố Vinh ngoài việc phát hiện", "start": 875.04, "duration": 3.78}, {"text": "nhiều điểm kinh doanh bóng cười cơ quan", "start": 876.899, "duration": 3.06}, {"text": "chức năng còn phát hiện nhiều sản phẩm", "start": 878.82, "duration": 2.879}, {"text": "thuốc lá điện tử có hàm lượng chất kích", "start": 879.959, "duration": 5.12}, {"text": "thích mạnh nguy hiểm cho người sử dụng", "start": 881.699, "duration": 3.38}, {"text": "tại 5 đầu mối phân phối kinh doanh thuốc", "start": 885.32, "duration": 4.6}, {"text": "lá điện tử bóng cười ở huyện Diễn Châu", "start": 888.0, "duration": 4.32}, {"text": "lực lượng chức năng thu giữ hơn 17.000", "start": 889.92, "duration": 5.099}, {"text": "thuốc lá điện tử hàng chục bình khí N2O", "start": 892.32, "duration": 5.699}, {"text": "gần 1.000 quả bóng cười cơ quan chức", "start": 895.019, "duration": 4.981}, {"text": "năng còn tạm giữ hình sự sự một nghi can", "start": 898.019, "duration": 3.721}, {"text": "cầm đầu đường dây phân phối kinh doanh", "start": 900.0, "duration": 3.72}, {"text": "các hàng hóa này ở huyện Diễn Châu và", "start": 901.74, "duration": 4.5}, {"text": "các địa phương lân cận Công An thành phố", "start": 903.72, "duration": 3.96}, {"text": "Vinh cũng thực hiện hàng chục cuộc kiểm", "start": 906.24, "duration": 3.719}, {"text": "tra trên địa bàn giữ gần 20.000 sản phẩm", "start": 907.68, "duration": 4.92}, {"text": "gồm thuốc lá điện tử tinh dầu sử dụng", "start": 909.959, "duration": 5.161}, {"text": "thuốc lá điện tử các loại đầu đốt linh", "start": 912.6, "duration": 5.22}, {"text": "kiện phụ kiện phương thức hoạt động của", "start": 915.12, "duration": 5.1}, {"text": "các đối tượng là tìm cách móc nối tiêu", "start": 917.82, "duration": 4.139}, {"text": "thụ thuốc lá điện tử nhằm vào giới trẻ", "start": 920.22, "duration": 4.44}, {"text": "dùng thủ đoạn lập các chân rết tiêu thụ", "start": 921.959, "duration": 5.06}, {"text": "bên trong các trường học", "start": 924.66, "duration": 5.16}, {"text": "tiếp tục vụ thông tin bảo vệ đánh nhau", "start": 927.019, "duration": 4.661}, {"text": "với người dân tại cảng biển An Thới", "start": 929.82, "duration": 3.72}, {"text": "thành phố Phú Quốc gây xôn xao dư luận", "start": 931.68, "duration": 3.899}, {"text": "hôm nay cơ quan cảnh sát điều tra công", "start": 933.54, "duration": 3.78}, {"text": "an thành phố Phú Quốc cho biết đã bắt", "start": 935.579, "duration": 3.841}, {"text": "tạm giam 8 đối tượng để phục vụ công tác", "start": 937.32, "duration": 3.98}, {"text": "điều tra", "start": 939.42, "duration": 4.38}, {"text": "cơ quan chức năng đã tạm giam 8 đối", "start": 941.3, "duration": 4.719}, {"text": "tượng gồm Vũ Mạnh Cường Long Trần Thương", "start": 943.8, "duration": 4.86}, {"text": "Huỳnh Tấn Đạt Đoàn Văn như gió bá trình", "start": 946.019, "duration": 5.221}, {"text": "Trần Văn tiền Lâm Hoàng kiểng và Lưu Văn", "start": 948.66, "duration": 5.34}, {"text": "nuôi trước đó khoảng 16 giờ ngày 26/4", "start": 951.24, "duration": 5.159}, {"text": "tại khu vực cảng biển An Thới lực lượng", "start": 954.0, "duration": 4.019}, {"text": "bảo vệ của công ty trách nhiệm hữu hạn", "start": 956.399, "duration": 4.56}, {"text": "cảng quốc tế An Thới đã xô xát với các", "start": 958.019, "duration": 4.861}, {"text": "hộ kinh doanh tại khu vực cạn nguyên", "start": 960.959, "duration": 3.721}, {"text": "nhân ban đầu được xác định là xuất phát", "start": 962.88, "duration": 3.6}, {"text": "từ việc tranh cãi giá thuê mặt bằng để", "start": 964.68, "duration": 4.32}, {"text": "làm dịch vụ dù gì đã khiến 3 người bị", "start": 966.48, "duration": 4.32}, {"text": "thương hiện công an thành phố Phú Quốc", "start": 969.0, "duration": 4.079}, {"text": "đang tiếp tục mở rộng điều tra vụ án để", "start": 970.8, "duration": 4.08}, {"text": "xử lý các đối tượng theo quy định của", "start": 973.079, "duration": 2.841}, {"text": "pháp luật", "start": 974.88, "duration": 4.139}, {"text": "giải Marathon lớn nhất ở general năm nay", "start": 975.92, "duration": 5.56}, {"text": "thu hút hơn 3.000 người đến từ 23 quốc", "start": 979.019, "duration": 4.44}, {"text": "gia tham gia giải này thường có tên là", "start": 981.48, "duration": 3.479}, {"text": "marathones", "start": 983.459, "duration": 3.841}, {"text": "it cool ngoài 3 cự ly Marathon khác nhau", "start": 984.959, "duration": 4.5}, {"text": "thì cuộc đua còn thử thách nhiều vận", "start": 987.3, "duration": 4.62}, {"text": "động viên vì diễn ra ở độ cao 1.600 M", "start": 989.459, "duration": 5.0}, {"text": "trên mặt nước biển", "start": 991.92, "duration": 5.52}, {"text": "cuộc đua xuất phát từ bờ Bắc của Hồ EXID", "start": 994.459, "duration": 5.56}, {"text": "cool tại trường đua hipolome nơi xuất", "start": 997.44, "duration": 5.28}, {"text": "phát và cũng là đích đến của cuộc đua lộ", "start": 1000.019, "duration": 4.701}, {"text": "trình thi đấu là các con đường dọc bờ hồ", "start": 1002.72, "duration": 4.979}, {"text": "trong buổi sáng gió nhẹ từ hồ trên núi", "start": 1004.72, "duration": 5.2}, {"text": "lớn thứ hai thế giới đã tiếp thêm sức", "start": 1007.699, "duration": 3.781}, {"text": "cho các vận động viên thực hiện hết hành", "start": 1009.92, "duration": 2.359}, {"text": "trình", "start": 1011.48, "duration": 3.24}, {"text": "chung cuộc huy chương vàng ở nội dung", "start": 1012.279, "duration": 4.901}, {"text": "Nam thuộc về shokudalatop bình luận", "start": 1014.72, "duration": 4.26}, {"text": "Uzbekistan", "start": 1017.18, "duration": 4.44}, {"text": "còn ở nội dung nữ dép hay đia brofo", "start": 1018.98, "duration": 5.64}, {"text": "khieva từ Ukraina đã về nhất và nhận huy", "start": 1021.62, "duration": 4.699}, {"text": "chương vàng", "start": 1024.62, "duration": 5.219}, {"text": "tại giải đua xe đạp Rio Italia cácurơ", "start": 1026.319, "duration": 5.98}, {"text": "bước vào trận thi đấu thứ 8 từ tadi đến", "start": 1029.839, "duration": 6.6}, {"text": "foxs chặng đua dài 207 km này được đánh", "start": 1032.299, "duration": 7.941}, {"text": "giá là đầy khó khăn do có nhiều đợt dốc", "start": 1036.439, "duration": 7.081}, {"text": "sau 80 km đầu tiên nhóm 13 tay đua bước", "start": 1040.24, "duration": 5.319}, {"text": "ra để vượt lên dẫn trước trong đó có", "start": 1043.52, "duration": 4.439}, {"text": "further Allen Bentley đội hình này duy", "start": 1045.559, "duration": 4.981}, {"text": "trì cho đến 50 km cuối penthully bước", "start": 1047.959, "duration": 4.681}, {"text": "lên dẫn đầu đoàn đua sau đó dần nới rộng", "start": 1050.54, "duration": 4.379}, {"text": "khoảng cách với top bám đuổi vị trí này", "start": 1052.64, "duration": 4.56}, {"text": "được Heli duy trì đến cuối cuộc đua và", "start": 1054.919, "duration": 5.461}, {"text": "anh cán đích với thành tích 4h44 giây", "start": 1057.2, "duration": 6.979}, {"text": "vậy nhì là vận động viên người Canada", "start": 1060.38, "duration": 7.56}, {"text": "Philippines của Italia báo hồng đứng đầu", "start": 1064.179, "duration": 6.041}, {"text": "bảng xếp hạng Andreas Nation và sau", "start": 1067.94, "duration": 4.5}, {"text": "hullie 5 phút 8 giây tổng thành tích", "start": 1070.22, "duration": 4.92}, {"text": "hiện tại của anh dẫn xếp đầu với 33 giờ", "start": 1072.44, "duration": 5.18}, {"text": "52 phút 10 giây", "start": 1075.14, "duration": 5.399}, {"text": "thông tin Chiều nay cơn bão có tên quốc", "start": 1077.62, "duration": 4.9}, {"text": "tế là Mocha đã đổ bộ vào bờ biển", "start": 1080.539, "duration": 4.561}, {"text": "Bangladesh và Myanmar báo một Kha có sức", "start": 1082.52, "duration": 5.519}, {"text": "gió lên tới 220 km một giờ và nhiều khả", "start": 1085.1, "duration": 4.8}, {"text": "năng gây ra lũ lụt diện rộng ở khu vực", "start": 1088.039, "duration": 4.88}, {"text": "tiếp giáp Vịnh bengal", "start": 1089.9, "duration": 5.46}, {"text": "các đoạn video chia sẻ trên mạng xã hội", "start": 1092.919, "duration": 4.181}, {"text": "cho thấy nhiều ngôi nhà đã bị tốc mái", "start": 1095.36, "duration": 3.66}, {"text": "bạn quảng cáo bày tỏ các tòa nhà ở", "start": 1097.1, "duration": 4.439}, {"text": "yangon giữa trời mưa như trút nước một", "start": 1099.02, "duration": 4.08}, {"text": "tháp viễn thông ở thành phố sideway", "start": 1101.539, "duration": 4.081}, {"text": "Myanmar đã bị gió lớn đánh sập khi cơn", "start": 1103.1, "duration": 5.16}, {"text": "bão tiến đến gần trước đó một ngày cảnh", "start": 1105.62, "duration": 4.26}, {"text": "sát Myanmar đã cảnh báo người dân tìm", "start": 1108.26, "duration": 3.5}, {"text": "nơi trú ẩn và tránh xa khu vực bãi biển", "start": 1109.88, "duration": 4.799}, {"text": "hiện trường học công sở và các cơ sở tôn", "start": 1111.76, "duration": 4.6}, {"text": "giáo là nơi tiếp nhận nhiều người dân", "start": 1114.679, "duration": 4.62}, {"text": "đến trú bão tại Bangladesh gió giật mạnh", "start": 1116.36, "duration": 5.4}, {"text": "bắt đầu thổi kèm theo mưa lớn báo mua", "start": 1119.299, "duration": 4.141}, {"text": "Kha có thể gây ra nhiều trận lở đất và", "start": 1121.76, "duration": 3.36}, {"text": "lũ lụt nghiêm trọng tại những nơi nó đi", "start": 1123.44, "duration": 3.54}, {"text": "qua theo các chuyên gia dự báo thời tiết", "start": 1125.12, "duration": 3.96}, {"text": "Bảo mua Kha là cơn bão mạnh nhất ở", "start": 1126.98, "duration": 4.319}, {"text": "banglades trong gần 2 thập kỷ qua nhà", "start": 1129.08, "duration": 3.66}, {"text": "chức trách nước này đã sơ tán khoảng", "start": 1131.299, "duration": 4.941}, {"text": "500.000 người đến khu vực an toàn", "start": 1132.74, "duration": 5.76}, {"text": "thông tin vừa rồi cũng đã khép lại", "start": 1136.24, "duration": 4.299}, {"text": "chương trình 60 Giây chiều nay Cảm ơn sự", "start": 1138.5, "duration": 3.96}, {"text": "quan tâm theo dõi của quý vị Hẹn gặp lại", "start": 1140.539, "duration": 4.321}, {"text": "quý vị trên HTV7 và HTV9 vào chương", "start": 1142.46, "duration": 4.14}, {"text": "trình 60 Giây sáng mai với những thông", "start": 1144.86, "duration": 3.66}, {"text": "tin luôn được cập nhật Xin kính chào tạm", "start": 1146.6, "duration": 3.92}, {"text": "biệt", "start": 1148.52, "duration": 2.0}, {"text": "[âm nhạc]", "start": 1154.32, "duration": 3.299}]